mendable/__init__.py
mendable/chatapp.py
mendable_py-0.0.6.dist-info/METADATA
mendable_py-0.0.6.dist-info/WHEEL
mendable_py-0.0.6.dist-info/top_level.txt
mendable_py-0.0.6.dist-info/RECORD
