Metadata-Version: 2.1
Name: mendable-py
Version: 0.0.6
Summary: Python SDK for Mendable.ai
Home-page: https://github.com/mendableai/mendable-py
Author: Eric Ciarla
Author-email: eric@mendable.ai
License: UNKNOWN
Platform: UNKNOWN
Requires-Dist: requests
